<?xml version="1.0" encoding="UTF-8"?>
<!DOCTYPE beans PUBLIC "-//SPRING//DTD BEAN//EN"
    "http://www.springframework.org/dtd/spring-beans.dtd">

<!-- 配置urlMapping -->
<beans default-autowire="byName">
	<bean id="appHandlerMapping"
		class="org.springframework.web.servlet.handler.SimpleUrlHandlerMapping">
		<property name="mappings">
			<value>
				/login.do=LoginController
				/em.do=EmployeeController
				/pj.do=ProjectController
				/pj_d.do=ProjectController_d
				/workreport.do=WorkReportController
				/depart.do=DepartmentController
				/assets.do=AssetsController
				/cost.do=CostController
				/menu.do=MenuController
				/plan.do=PlanController
				/plantype.do=PlanTypeController
				/goods.do=GoodsController
				/card.do=CardController
				/finance.do=FinanceController
				/pos.do=PosController
				/search.do=SearchController
				/excel.do=ExcelController
				/train.do=TrainController
				/holiday.do=HolidayController
				/car.do=CarController
				/infoequip.do=InfoEquipController
				/customequip.do=CustomEquipController
				/tree.do=TreeController
				/role.do=RoleController
				/visit.do=VisitController
				/ins.do=InsController
				/contract.do=ContractController
				/c_apply.do=ContractController_Apply
				/c_budget.do=ContractController_Budget
				/c_pay.do=ContractController_Pay
				/b_contract.do=BudgetController_contract
				/b_credited.do=BudgetController_credited
				/b_increase.do=BudgetController_increase
				/b_remain.do=BudgetController_remain
			</value>
		</property>
	</bean>

<!-- viewResolver 视图解析器,将视图名(ModelAndView中的view)解析成URL-->
	<bean id="viewResolver"
		class="org.springframework.web.servlet.view.InternalResourceViewResolver">
		<property name="suffix" value=".jsp" />
		<property name="viewClass"
			value="org.springframework.web.servlet.view.InternalResourceView" />
	</bean>

<!--multipartResolver 支持分段文件上传 使用时form需要加上enctype="multipart/form-data"属性,且form的method设置为POST-->
	<bean id="multipartResolver"
		class="org.springframework.web.multipart.commons.CommonsMultipartResolver">
		<property name="maxUploadSize" value="500400000" />
		<property name="maxInMemorySize" value="4096" />
    </bean>

<!-- 定义上面urlMapping所对应的类 -->
	<bean name="LoginController" class="com.basesoft.modules.login.LoginController" />
	<bean name="EmployeeController" class="com.basesoft.modules.employee.EmployeeController" />
	<bean name="ProjectController" class="com.basesoft.modules.project.ProjectController" />
	<bean name="ProjectController_d" class="com.basesoft.modules.project.ProjectController_d" />
	<bean name="WorkReportController" class="com.basesoft.modules.workreport.WorkReportController" />
	<bean name="DepartmentController" class="com.basesoft.modules.depart.DepartmentController" />
	<bean name="AssetsController" class="com.basesoft.modules.assets.AssetsController"></bean>
	<bean name="CostController" class="com.basesoft.modules.cost.CostController"></bean>
	<bean name="MenuController" class="com.basesoft.modules.menu.MenuController"></bean>
	<bean name="PlanController" class="com.basesoft.modules.plan.PlanController"></bean>
	<bean name="PlanTypeController" class="com.basesoft.modules.plan.PlanTypeController"></bean>
	<bean name="GoodsController" class="com.basesoft.modules.goods.GoodsController"></bean>
	<bean name="CardController" class="com.basesoft.modules.employee.CardController"></bean>
	<bean name="FinanceController" class="com.basesoft.modules.employee.FinanceController"></bean>
	<bean name="PosController" class="com.basesoft.modules.employee.PosController"></bean>
	<bean name="SearchController" class="com.basesoft.modules.employee.SearchController"></bean>
	<bean name="ExcelController" class="com.basesoft.modules.excel.ExcelController"></bean>
	<bean name="TrainController" class="com.basesoft.modules.employee.TrainController"></bean>
	<bean name="HolidayController" class="com.basesoft.modules.employee.HolidayController"></bean>
	<bean name="CarController" class="com.basesoft.modules.employee.CarController"></bean>
	<bean name="InfoEquipController" class="com.basesoft.modules.infoequip.InfoEquipController"></bean>
	<bean name="CustomEquipController" class="com.basesoft.modules.customequip.CustomEquipController"></bean>
	<bean name="TreeController" class="com.basesoft.util.TreeController"></bean>
	<bean name="RoleController" class="com.basesoft.modules.role.RoleController"></bean>
	<bean name="VisitController" class="com.basesoft.modules.visit.VisitController"></bean>
	<bean name="InsController" class="com.basesoft.modules.ins.InsController"></bean>
	<bean name="ContractController" class="com.basesoft.modules.contract.ContractController"></bean>
	<bean name="ContractController_Apply" class="com.basesoft.modules.contract.ContractController_Apply"></bean>
	<bean name="ContractController_Budget" class="com.basesoft.modules.contract.ContractController_Budget"></bean>
	<bean name="ContractController_Pay" class="com.basesoft.modules.contract.ContractController_Pay"></bean>
	<bean name="BudgetController_contract" class="com.basesoft.modules.budget.BudgetController_contract"></bean>
	<bean name="BudgetController_credited" class="com.basesoft.modules.budget.BudgetController_credited"></bean>
	<bean name="BudgetController_increase" class="com.basesoft.modules.budget.BudgetController_increase"></bean>
	<bean name="BudgetController_remain" class="com.basesoft.modules.budget.BudgetController_remain"></bean>
</beans>

